{
    "Mark Twain": {
        "name": "Mark Twain",
        "info": [
            {
              "position": "Project Leader",
              "yearincome": "24000",
            }
        ]
    },
    "John Doe": {
        "name": "Chase",
        "info": [
            {
              "position": "Senior Programmer",
              "yearincome": "115000",
            }
        ]
    },
    "Bob Johnson": {
        "name": "Bob Johnson",
        "info": [
            {
              "position": "Junior Programmer",
              "yearincome": "67000",
            }
        ]
    },
    "Marth Lewis": {
        "name": "Marth Lewis",
        "info": [
            {
              "position": "Senior Programmer",
              "yearincome": "135000",
            }
        ]
    }
}
